detox/__init__.py
detox/__main__.py
detox/logger.py
detox/runner.py
detox_jar-1.1.0.dist-info/LICENSE
detox_jar-1.1.0.dist-info/METADATA
detox_jar-1.1.0.dist-info/WHEEL
detox_jar-1.1.0.dist-info/entry_points.txt
detox_jar-1.1.0.dist-info/top_level.txt
detox_jar-1.1.0.dist-info/RECORD
