Metadata-Version: 2.1
Name: detox-jar
Version: 1.1.0
Summary: Command line automation tool in pure Python
Author-email: Kaloyan Ivanov <kaloyan.ivanov88@gmail.com>
License: MIT License
Project-URL: repository, https://github.com/kaliv0/detox-jar.git
Keywords: automation,cli tool,command line runner
Requires-Python: >=3.11
License-File: LICENSE
Requires-Dist: pyyaml>=6.0.2
Provides-Extra: dev
Requires-Dist: ruff>=0.7.3; extra == "dev"
Requires-Dist: build>=1.2.2; extra == "dev"
Requires-Dist: twine>=5.1.1; extra == "dev"
